nsls2forge_utils/__init__.py
nsls2forge_utils/_version.py
nsls2forge_utils/all_feedstocks.py
nsls2forge_utils/auto_tick.py
nsls2forge_utils/check_results.py
nsls2forge_utils/cli.py
nsls2forge_utils/dashboard.py
nsls2forge_utils/git_utils.py
nsls2forge_utils/graph_utils.py
nsls2forge_utils/io.py
nsls2forge_utils/meta_utils.py
nsls2forge_utils/tests/__init__.py
nsls2forge_utils/tests/conftest.py
nsls2forge_utils/tests/test_all_feedstocks.py
nsls2forge_utils/tests/test_check_results.py
nsls2forge_utils/tests/test_check_results.sh
nsls2forge_utils/tests/test_dashboard.py
nsls2forge_utils/tests/test_extract_github_org_and_repo_from_url.py
nsls2forge_utils-0.1.3.dist-info/AUTHORS.rst
nsls2forge_utils-0.1.3.dist-info/LICENSE
nsls2forge_utils-0.1.3.dist-info/METADATA
nsls2forge_utils-0.1.3.dist-info/WHEEL
nsls2forge_utils-0.1.3.dist-info/entry_points.txt
nsls2forge_utils-0.1.3.dist-info/top_level.txt
nsls2forge_utils-0.1.3.dist-info/RECORD
